setup.cfg
setup.py
simab/__init__.py
simab.egg-info/PKG-INFO
simab.egg-info/SOURCES.txt
simab.egg-info/dependency_links.txt
simab.egg-info/requires.txt
simab.egg-info/top_level.txt
simab.egg-info/zip-safe
simab/algorithms/__init__.py
simab/algorithms/algorithm.py
simab/algorithms/epsilon_first.py
simab/algorithms/epsilon_greedy.py
simab/algorithms/oracle.py
simab/algorithms/random_choice.py
simab/algorithms/single_arm.py
simab/algorithms/softmax.py
simab/algorithms/ucb1.py
simab/arms/__init__.py
simab/arms/arm.py
simab/arms/gmm.py
simab/arms/normal.py
simab/simulation/__init__.py
simab/simulation/parameter_tuning.py
simab/simulation/simulator.py